{
    "name": "C_100nF_0402",
    "revision": "",
    "IPN": "",
    "description": "Ceramic capacitor, 100nF in 0402 SMD package",
    "keywords": "cap smd ceramic",
    "units": "",
    "minimum_stock": 0.0,
    "assembly": false,
    "component": true,
    "trackable": false,
    "purchaseable": true,
    "salable": false,
    "virtual": false,
    "is_template": false,
    "variant_of": null,
    "validated_bom": false,
    "image": "",
    "thumbnail": "",
    "suppliers": [
        {
            "supplier_name": "DigiKey",
            "SKU": "1276-6720-2-ND",
            "description": "CAP CER 0.1UF 25V X7R 0402",
            "link": "https://www.digikey.com/product-detail/en/samsung-electro-mechanics/CL05B104KA5NNNC/1276-6720-2-ND/5961204",
            "note": null,
            "packaging": null,
            "price_breaks": [
                {
                    "quantity": 1.0,
                    "price": 985.0,
                    "price_currency": "USD"
                },
                {
                    "quantity": 20.0,
                    "price": 2.35,
                    "price_currency": "USD"
                },
                {
                    "quantity": 100.0,
                    "price": 0.2662,
                    "price_currency": "USD"
                },
                {
                    "quantity": 1000.0,
                    "price": 0.184,
                    "price_currency": "USD"
                }
            ],
            "manufacturer_name": "Samsung_Electro-Mechanics",
            "MPN": "CL05B104KA5NNNC",
            "mp_description": null,
            "mp_link": null
        },
        {
            "supplier_name": "DigiKey",
            "SKU": "1276-1002-2-ND",
            "description": "CAP CER 0.1UF 10V X7R 0402",
            "link": "https://www.digikey.com/product-detail/en/samsung-electro-mechanics/CL05B104KP5NNNC/1276-1002-2-ND/3886660",
            "note": null,
            "packaging": null,
            "price_breaks": [
                {
                    "quantity": 1.0,
                    "price": 985.0,
                    "price_currency": "USD"
                },
                {
                    "quantity": 20.0,
                    "price": 2.35,
                    "price_currency": "USD"
                },
                {
                    "quantity": 100.0,
                    "price": 0.2662,
                    "price_currency": "USD"
                },
                {
                    "quantity": 1000.0,
                    "price": 0.184,
                    "price_currency": "USD"
                }
            ],
            "manufacturer_name": "Samsung_Electro-Mechanics",
            "MPN": "CL05B104KP5NNNC",
            "mp_description": null,
            "mp_link": null
        },
        {
            "supplier_name": "Mouser",
            "SKU": "MOU-25510-MCM",
            "description": null,
            "link": null,
            "note": null,
            "packaging": null,
            "price_breaks": [
                {
                    "quantity": 1.0,
                    "price": 985.0,
                    "price_currency": "USD"
                },
                {
                    "quantity": 20.0,
                    "price": 2.35,
                    "price_currency": "USD"
                },
                {
                    "quantity": 100.0,
                    "price": 0.2662,
                    "price_currency": "USD"
                },
                {
                    "quantity": 1000.0,
                    "price": 0.184,
                    "price_currency": "USD"
                }
            ]
        },
        {
            "supplier_name": "Arrow",
            "SKU": "ARR-91700-VGE",
            "description": null,
            "link": null,
            "note": null,
            "packaging": null,
            "price_breaks": [
                {
                    "quantity": 1.0,
                    "price": 985.0,
                    "price_currency": "USD"
                },
                {
                    "quantity": 20.0,
                    "price": 2.35,
                    "price_currency": "USD"
                },
                {
                    "quantity": 100.0,
                    "price": 0.2662,
                    "price_currency": "USD"
                },
                {
                    "quantity": 1000.0,
                    "price": 0.184,
                    "price_currency": "USD"
                }
            ]
        },
        {
            "supplier_name": "LCSC",
            "SKU": "LCS-85964-TDY",
            "description": null,
            "link": null,
            "note": null,
            "packaging": null,
            "price_breaks": [
                {
                    "quantity": 1.0,
                    "price": 985.0,
                    "price_currency": "USD"
                },
                {
                    "quantity": 20.0,
                    "price": 2.35,
                    "price_currency": "USD"
                },
                {
                    "quantity": 100.0,
                    "price": 0.2662,
                    "price_currency": "USD"
                },
                {
                    "quantity": 1000.0,
                    "price": 0.184,
                    "price_currency": "USD"
                }
            ]
        },
        {
            "supplier_name": "Newark",
            "SKU": "NEW-83020-HAR",
            "description": null,
            "link": null,
            "note": null,
            "packaging": null,
            "price_breaks": [
                {
                    "quantity": 1.0,
                    "price": 985.0,
                    "price_currency": "USD"
                },
                {
                    "quantity": 20.0,
                    "price": 2.35,
                    "price_currency": "USD"
                },
                {
                    "quantity": 100.0,
                    "price": 0.2662,
                    "price_currency": "USD"
                },
                {
                    "quantity": 1000.0,
                    "price": 0.184,
                    "price_currency": "USD"
                }
            ]
        },
        {
            "supplier_name": "Future",
            "SKU": "FUT-04471-WZT",
            "description": null,
            "link": null,
            "note": null,
            "packaging": null,
            "price_breaks": [
                {
                    "quantity": 1.0,
                    "price": 985.0,
                    "price_currency": "USD"
                },
                {
                    "quantity": 20.0,
                    "price": 2.35,
                    "price_currency": "USD"
                },
                {
                    "quantity": 100.0,
                    "price": 0.2662,
                    "price_currency": "USD"
                },
                {
                    "quantity": 1000.0,
                    "price": 0.184,
                    "price_currency": "USD"
                }
            ]
        }
    ]
}
