{
    "name": "R_10K_0805_1%",
    "revision": "",
    "IPN": null,
    "description": "10K resistor in 0805 SMD package",
    "keywords": "resistor smd 0805",
    "units": "",
    "minimum_stock": 0.0,
    "assembly": false,
    "component": true,
    "trackable": false,
    "purchaseable": true,
    "salable": false,
    "virtual": false,
    "is_template": false,
    "variant_of_name": null,
    "image": "",
    "thumbnail": "",
    "suppliers": [
        {
            "supplier_name": "DigiKey",
            "SKU": "RR12P10.0KDTR-ND",
            "description": "RES SMD 10K OHM 0.5% 1/10W 0805",
            "link": "https://www.digikey.com/product-detail/en/susumu/RR1220P-103-D/RR12P10.0KDTR-ND/432315",
            "note": null,
            "packaging": null,
            "price_breaks": [
                {
                    "quantity": 1.0,
                    "price": 985.0,
                    "price_currency": "USD"
                },
                {
                    "quantity": 20.0,
                    "price": 2.35,
                    "price_currency": "USD"
                },
                {
                    "quantity": 100.0,
                    "price": 0.2662,
                    "price_currency": "USD"
                },
                {
                    "quantity": 1000.0,
                    "price": 0.184,
                    "price_currency": "USD"
                }
            ],
            "manufacturer_name": "Susumu",
            "MPN": "RR1220P-103-D",
            "mp_description": null,
            "mp_link": null
        },
        {
            "supplier_name": "DigiKey",
            "SKU": "P10KDATR-ND",
            "description": "RES 10K OHM 0.1% 1/8W 0805",
            "link": "https://www.digikey.com/product-detail/en/panasonic-electronic-components/ERA-6AEB103V/P10KDATR-ND/1465773",
            "note": null,
            "packaging": null,
            "price_breaks": [
                {
                    "quantity": 1.0,
                    "price": 985.0,
                    "price_currency": "USD"
                },
                {
                    "quantity": 20.0,
                    "price": 2.35,
                    "price_currency": "USD"
                },
                {
                    "quantity": 100.0,
                    "price": 0.2662,
                    "price_currency": "USD"
                },
                {
                    "quantity": 1000.0,
                    "price": 0.184,
                    "price_currency": "USD"
                }
            ],
            "manufacturer_name": "Panasonic_Electronic_Components",
            "MPN": "ERA-6AEB103V",
            "mp_description": null,
            "mp_link": null
        },
        {
            "supplier_name": "DigiKey",
            "SKU": "A110639TR-ND",
            "description": "RES SMD 10K OHM 0.1% 1/4W 0805",
            "link": "https://www.digikey.com/product-detail/en/te-connectivity-passive-product/2176093-5/A110639TR-ND/4034107",
            "note": null,
            "packaging": null,
            "price_breaks": [
                {
                    "quantity": 1.0,
                    "price": 985.0,
                    "price_currency": "USD"
                },
                {
                    "quantity": 20.0,
                    "price": 2.35,
                    "price_currency": "USD"
                },
                {
                    "quantity": 100.0,
                    "price": 0.2662,
                    "price_currency": "USD"
                },
                {
                    "quantity": 1000.0,
                    "price": 0.184,
                    "price_currency": "USD"
                }
            ],
            "manufacturer_name": "TE_Connectivity_Passive_Product",
            "MPN": "2176093-5",
            "mp_description": null,
            "mp_link": null
        },
        {
            "supplier_name": "DigiKey",
            "SKU": "RG20N10.0KWTR-ND",
            "description": "RES SMD 10K OHM 0.05% 1/8W 0805",
            "link": "https://www.digikey.com/product-detail/en/susumu/RG2012N-103-W-T1/RG20N10.0KWTR-ND/600712",
            "note": null,
            "packaging": null,
            "price_breaks": [
                {
                    "quantity": 1.0,
                    "price": 985.0,
                    "price_currency": "USD"
                },
                {
                    "quantity": 20.0,
                    "price": 2.35,
                    "price_currency": "USD"
                },
                {
                    "quantity": 100.0,
                    "price": 0.2662,
                    "price_currency": "USD"
                },
                {
                    "quantity": 1000.0,
                    "price": 0.184,
                    "price_currency": "USD"
                }
            ],
            "manufacturer_name": "Susumu",
            "MPN": "RG2012N-103-W-T1",
            "mp_description": null,
            "mp_link": null
        },
        {
            "supplier_name": "Mouser",
            "SKU": "MOU-62329-PYU",
            "description": null,
            "link": null,
            "note": null,
            "packaging": null,
            "price_breaks": [
                {
                    "quantity": 1.0,
                    "price": 985.0,
                    "price_currency": "USD"
                },
                {
                    "quantity": 20.0,
                    "price": 2.35,
                    "price_currency": "USD"
                },
                {
                    "quantity": 100.0,
                    "price": 0.2662,
                    "price_currency": "USD"
                },
                {
                    "quantity": 1000.0,
                    "price": 0.184,
                    "price_currency": "USD"
                }
            ]
        },
        {
            "supplier_name": "Arrow",
            "SKU": "ARR-17000-JCK",
            "description": null,
            "link": null,
            "note": null,
            "packaging": null,
            "price_breaks": [
                {
                    "quantity": 1.0,
                    "price": 985.0,
                    "price_currency": "USD"
                },
                {
                    "quantity": 20.0,
                    "price": 2.35,
                    "price_currency": "USD"
                },
                {
                    "quantity": 100.0,
                    "price": 0.2662,
                    "price_currency": "USD"
                },
                {
                    "quantity": 1000.0,
                    "price": 0.184,
                    "price_currency": "USD"
                }
            ]
        },
        {
            "supplier_name": "LCSC",
            "SKU": "LCS-66409-BOA",
            "description": null,
            "link": null,
            "note": null,
            "packaging": null,
            "price_breaks": [
                {
                    "quantity": 1.0,
                    "price": 985.0,
                    "price_currency": "USD"
                },
                {
                    "quantity": 20.0,
                    "price": 2.35,
                    "price_currency": "USD"
                },
                {
                    "quantity": 100.0,
                    "price": 0.2662,
                    "price_currency": "USD"
                },
                {
                    "quantity": 1000.0,
                    "price": 0.184,
                    "price_currency": "USD"
                }
            ]
        },
        {
            "supplier_name": "Newark",
            "SKU": "NEW-33779-RAN",
            "description": null,
            "link": null,
            "note": null,
            "packaging": null,
            "price_breaks": [
                {
                    "quantity": 1.0,
                    "price": 985.0,
                    "price_currency": "USD"
                },
                {
                    "quantity": 20.0,
                    "price": 2.35,
                    "price_currency": "USD"
                },
                {
                    "quantity": 100.0,
                    "price": 0.2662,
                    "price_currency": "USD"
                },
                {
                    "quantity": 1000.0,
                    "price": 0.184,
                    "price_currency": "USD"
                }
            ]
        },
        {
            "supplier_name": "Future",
            "SKU": "FUT-22116-XMC",
            "description": null,
            "link": null,
            "note": null,
            "packaging": null,
            "price_breaks": [
                {
                    "quantity": 1.0,
                    "price": 985.0,
                    "price_currency": "USD"
                },
                {
                    "quantity": 20.0,
                    "price": 2.35,
                    "price_currency": "USD"
                },
                {
                    "quantity": 100.0,
                    "price": 0.2662,
                    "price_currency": "USD"
                },
                {
                    "quantity": 1000.0,
                    "price": 0.184,
                    "price_currency": "USD"
                }
            ]
        }
    ]
}
