{
    "pk": 39,
    "name": "LCSC",
    "description": "Electronic components distributor",
    "website": "https://lcsc.com/",
    "phone": "",
    "address": "77673 Bishop Turnpike, 74969, North Cheryl, Hawaii, Portugal",
    "email": "",
    "currency": "USD",
    "contact": "",
    "link": "",
    "image": "/media/company_images/company_39_img.webp",
    "active": true,
    "is_customer": false,
    "is_manufacturer": false,
    "is_supplier": true,
    "parts_supplied": 60,
    "parts_manufactured": 0,
    "address_count": 2,
    "primary_address": {
        "pk": 60,
        "company": 39,
        "title": "Secondary Address",
        "primary": true,
        "line1": "77673 Bishop Turnpike",
        "line2": "",
        "postal_code": "74969",
        "postal_city": "North Cheryl",
        "province": "Hawaii",
        "country": "Portugal",
        "shipping_notes": "",
        "internal_shipping_notes": "",
        "link": ""
    },
    "tax_id": ""
}
