{
    "pk": 29,
    "name": "Texas Instruments",
    "description": "",
    "website": "https://www.ti.com/",
    "phone": "",
    "address": "264 David Villages, 97718, Lake Michael, New Mexico, Kenya",
    "email": "",
    "currency": "USD",
    "contact": "",
    "link": "",
    "image": "/media/company_images/company_29_img.jpg",
    "active": true,
    "is_customer": false,
    "is_manufacturer": true,
    "is_supplier": true,
    "parts_supplied": 0,
    "parts_manufactured": 1,
    "address_count": 2,
    "primary_address": {
        "pk": 68,
        "company": 29,
        "title": "Secondary Address",
        "primary": true,
        "line1": "264 David Villages",
        "line2": "",
        "postal_code": "97718",
        "postal_city": "Lake Michael",
        "province": "New Mexico",
        "country": "Kenya",
        "shipping_notes": "",
        "internal_shipping_notes": "",
        "link": ""
    },
    "tax_id": ""
}
